cirkel-0.2.data/purelib/cirkel/__init__.py
cirkel-0.2.data/purelib/cirkel/ccirkel.pyd
cirkel-0.2.data/purelib/cirkel/functions.py
cirkel-0.2.data/purelib/cirkel/example/example.py
cirkel-0.2.dist-info/DESCRIPTION.rst
cirkel-0.2.dist-info/METADATA
cirkel-0.2.dist-info/RECORD
cirkel-0.2.dist-info/WHEEL
cirkel-0.2.dist-info/metadata.json
cirkel-0.2.dist-info/top_level.txt
