Metadata-Version: 2.0
Name: cirkel
Version: 0.2
Summary: Automata plotting circles on canvas
Home-page: https://github.com/zmic/cirkel
Author: Michael Vanslembrouck
Author-email: UNKNOWN
License: MIT
Platform: UNKNOWN
Classifier: Development Status :: 3 - Alpha
Requires-Python: >=3.5
Requires-Dist: numpy
Requires-Dist: imageio
